<?xml version="1.0" encoding="UTF-8"?>
<export version="D">
  <design>
    <source>/home/stevew/munin3/munin3/munin3.sch</source>
    <date>Sun 31 Oct 2021 03:02:58 PM PDT</date>
    <tool>Eeschema 6.0.0-rc1-unknown-e7fa02a~66~ubuntu18.04.1</tool>
    <sheet number="1" name="/" tstamps="/">
      <title_block>
        <title/>
        <company/>
        <rev/>
        <date/>
        <source>munin3.sch</source>
        <comment number="1" value=""/>
        <comment number="2" value=""/>
        <comment number="3" value=""/>
        <comment number="4" value=""/>
      </title_block>
    </sheet>
  </design>
  <components>
    <comp ref="L1">
      <value>Transformer_1P_1S</value>
      <footprint>Transformer_THT:RF_Input_XFMR</footprint>
      <datasheet>~</datasheet>
      <libsource lib="Device" part="Transformer_1P_1S" description="Transformer, single primary, single secondary"/>
      <sheetpath names="/" tstamps="/"/>
      <tstamp>61480668</tstamp>
    </comp>
    <comp ref="R8">
      <value>100/1W</value>
      <footprint>Resistor_SMD:R_1812_4532Metric_Pad1.30x3.40mm_HandSolder</footprint>
      <datasheet>~</datasheet>
      <libsource lib="Device" part="R" description="Resistor"/>
      <sheetpath names="/" tstamps="/"/>
      <tstamp>61496FB3</tstamp>
    </comp>
    <comp ref="C8">
      <value>1nF</value>
      <footprint>Capacitor_SMD:C_0805_2012Metric_Pad1.15x1.40mm_HandSolder</footprint>
      <datasheet>~</datasheet>
      <libsource lib="Device" part="C" description="Unpolarized capacitor"/>
      <sheetpath names="/" tstamps="/"/>
      <tstamp>61497325</tstamp>
    </comp>
    <comp ref="C6">
      <value>10nF</value>
      <footprint>Capacitor_SMD:C_0805_2012Metric_Pad1.15x1.40mm_HandSolder</footprint>
      <datasheet>~</datasheet>
      <libsource lib="Device" part="C" description="Unpolarized capacitor"/>
      <sheetpath names="/" tstamps="/"/>
      <tstamp>61497D82</tstamp>
    </comp>
    <comp ref="C15">
      <value>1nF</value>
      <footprint>Capacitor_SMD:C_0805_2012Metric_Pad1.15x1.40mm_HandSolder</footprint>
      <datasheet>~</datasheet>
      <libsource lib="Device" part="C" description="Unpolarized capacitor"/>
      <sheetpath names="/" tstamps="/"/>
      <tstamp>61499740</tstamp>
    </comp>
    <comp ref="C13">
      <value>10nF</value>
      <footprint>Capacitor_SMD:C_0805_2012Metric_Pad1.15x1.40mm_HandSolder</footprint>
      <datasheet>~</datasheet>
      <libsource lib="Device" part="C" description="Unpolarized capacitor"/>
      <sheetpath names="/" tstamps="/"/>
      <tstamp>61499746</tstamp>
    </comp>
    <comp ref="R9">
      <value>1.5K</value>
      <footprint>Resistor_SMD:R_0805_2012Metric_Pad1.15x1.40mm_HandSolder</footprint>
      <datasheet>~</datasheet>
      <libsource lib="Device" part="R" description="Resistor"/>
      <sheetpath names="/" tstamps="/"/>
      <tstamp>6149A178</tstamp>
    </comp>
    <comp ref="R10">
      <value>1.5K</value>
      <footprint>Resistor_SMD:R_0805_2012Metric_Pad1.15x1.40mm_HandSolder</footprint>
      <datasheet>~</datasheet>
      <libsource lib="Device" part="R" description="Resistor"/>
      <sheetpath names="/" tstamps="/"/>
      <tstamp>6149AA59</tstamp>
    </comp>
    <comp ref="R5">
      <value>4.7</value>
      <footprint>Resistor_SMD:R_0805_2012Metric_Pad1.15x1.40mm_HandSolder</footprint>
      <datasheet>~</datasheet>
      <libsource lib="Device" part="R" description="Resistor"/>
      <sheetpath names="/" tstamps="/"/>
      <tstamp>6149CF87</tstamp>
    </comp>
    <comp ref="R4">
      <value>4.7</value>
      <footprint>Resistor_SMD:R_0805_2012Metric_Pad1.15x1.40mm_HandSolder</footprint>
      <datasheet>~</datasheet>
      <libsource lib="Device" part="R" description="Resistor"/>
      <sheetpath names="/" tstamps="/"/>
      <tstamp>6149E063</tstamp>
    </comp>
    <comp ref="R13">
      <value>4.7</value>
      <footprint>Resistor_SMD:R_0805_2012Metric_Pad1.15x1.40mm_HandSolder</footprint>
      <datasheet>~</datasheet>
      <libsource lib="Device" part="R" description="Resistor"/>
      <sheetpath names="/" tstamps="/"/>
      <tstamp>6149E61D</tstamp>
    </comp>
    <comp ref="R15">
      <value>4.7</value>
      <footprint>Resistor_SMD:R_0805_2012Metric_Pad1.15x1.40mm_HandSolder</footprint>
      <datasheet>~</datasheet>
      <libsource lib="Device" part="R" description="Resistor"/>
      <sheetpath names="/" tstamps="/"/>
      <tstamp>6149EE06</tstamp>
    </comp>
    <comp ref="C7">
      <value>10nF</value>
      <footprint>Capacitor_SMD:C_0805_2012Metric_Pad1.15x1.40mm_HandSolder</footprint>
      <datasheet>~</datasheet>
      <libsource lib="Device" part="C" description="Unpolarized capacitor"/>
      <sheetpath names="/" tstamps="/"/>
      <tstamp>61639394</tstamp>
    </comp>
    <comp ref="R7">
      <value>22</value>
      <footprint>Resistor_SMD:R_0805_2012Metric_Pad1.15x1.40mm_HandSolder</footprint>
      <datasheet>~</datasheet>
      <fields>
        <field name="Mouser Part Number">660-SG73P2ATTD220G</field>
      </fields>
      <libsource lib="Device" part="R" description="Resistor"/>
      <sheetpath names="/" tstamps="/"/>
      <tstamp>61639E9E</tstamp>
    </comp>
    <comp ref="R6">
      <value>22</value>
      <footprint>Resistor_SMD:R_0805_2012Metric_Pad1.15x1.40mm_HandSolder</footprint>
      <datasheet>~</datasheet>
      <fields>
        <field name="Mouser Part Number">660-SG73P2ATTD220G</field>
      </fields>
      <libsource lib="Device" part="R" description="Resistor"/>
      <sheetpath names="/" tstamps="/"/>
      <tstamp>6163A513</tstamp>
    </comp>
    <comp ref="C4">
      <value>100pF/500V/NPO</value>
      <footprint>Capacitor_SMD:C_0805_2012Metric_Pad1.15x1.40mm_HandSolder</footprint>
      <datasheet>~</datasheet>
      <fields>
        <field name="Mouser Part Number">603-CC206JRNPOBBN101</field>
      </fields>
      <libsource lib="Device" part="C" description="Unpolarized capacitor"/>
      <sheetpath names="/" tstamps="/"/>
      <tstamp>6163D173</tstamp>
    </comp>
    <comp ref="C14">
      <value>10nF</value>
      <footprint>Capacitor_SMD:C_0805_2012Metric_Pad1.15x1.40mm_HandSolder</footprint>
      <datasheet>~</datasheet>
      <libsource lib="Device" part="C" description="Unpolarized capacitor"/>
      <sheetpath names="/" tstamps="/"/>
      <tstamp>61641773</tstamp>
    </comp>
    <comp ref="R12">
      <value>22</value>
      <footprint>Resistor_SMD:R_0805_2012Metric_Pad1.15x1.40mm_HandSolder</footprint>
      <datasheet>~</datasheet>
      <fields>
        <field name="Mouser Part Number">660-SG73P2ATTD220G</field>
      </fields>
      <libsource lib="Device" part="R" description="Resistor"/>
      <sheetpath names="/" tstamps="/"/>
      <tstamp>616424C6</tstamp>
    </comp>
    <comp ref="R11">
      <value>22</value>
      <footprint>Resistor_SMD:R_0805_2012Metric_Pad1.15x1.40mm_HandSolder</footprint>
      <datasheet>~</datasheet>
      <fields>
        <field name="Mouser Part Number">660-SG73P2ATTD220G</field>
      </fields>
      <libsource lib="Device" part="R" description="Resistor"/>
      <sheetpath names="/" tstamps="/"/>
      <tstamp>61642B48</tstamp>
    </comp>
    <comp ref="C16">
      <value>100pF/500V/NPO</value>
      <footprint>Capacitor_SMD:C_1206_3216Metric_Pad1.42x1.75mm_HandSolder</footprint>
      <datasheet>~</datasheet>
      <fields>
        <field name="Mouser Part Number">603-CC206JRNPOBBN101</field>
      </fields>
      <libsource lib="Device" part="C" description="Unpolarized capacitor"/>
      <sheetpath names="/" tstamps="/"/>
      <tstamp>61645C4F</tstamp>
    </comp>
    <comp ref="L2">
      <value>Transformer-FB</value>
      <footprint>Transformer_THT:RF_FB_XFMR</footprint>
      <datasheet>~</datasheet>
      <libsource lib="Device" part="Transformer_1P_1S" description="Transformer, single primary, single secondary"/>
      <sheetpath names="/" tstamps="/"/>
      <tstamp>6164AAE7</tstamp>
    </comp>
    <comp ref="C12">
      <value>220pF/500V/NPO</value>
      <footprint>Capacitor_SMD:C_1206_3216Metric_Pad1.42x1.75mm_HandSolder</footprint>
      <datasheet>~</datasheet>
      <fields>
        <field name="Mouser Part Number">81-GRM31A5C2H221JW1D</field>
      </fields>
      <libsource lib="Device" part="C" description="Unpolarized capacitor"/>
      <sheetpath names="/" tstamps="/"/>
      <tstamp>61650807</tstamp>
    </comp>
    <comp ref="L3">
      <value>Transformer_1P_SS</value>
      <footprint>Transformer_THT:HF_Power_Xfmr</footprint>
      <datasheet>~</datasheet>
      <libsource lib="Device" part="Transformer_1P_SS" description="Transformer, single primary, split secondary"/>
      <sheetpath names="/" tstamps="/"/>
      <tstamp>6165D7D3</tstamp>
    </comp>
    <comp ref="L4">
      <value>FT-50-43</value>
      <footprint>Transformer_THT:RF_Choke</footprint>
      <datasheet>~</datasheet>
      <libsource lib="Device" part="L_Core_Iron_Small" description="Inductor with iron core, small symbol"/>
      <sheetpath names="/" tstamps="/"/>
      <tstamp>6166AB2B</tstamp>
    </comp>
    <comp ref="R19">
      <value>4.7</value>
      <footprint>Resistor_SMD:R_0805_2012Metric_Pad1.15x1.40mm_HandSolder</footprint>
      <datasheet>~</datasheet>
      <libsource lib="Device" part="R" description="Resistor"/>
      <sheetpath names="/" tstamps="/"/>
      <tstamp>6166D508</tstamp>
    </comp>
    <comp ref="R18">
      <value>4.7</value>
      <footprint>Resistor_SMD:R_0805_2012Metric_Pad1.15x1.40mm_HandSolder</footprint>
      <datasheet>~</datasheet>
      <libsource lib="Device" part="R" description="Resistor"/>
      <sheetpath names="/" tstamps="/"/>
      <tstamp>6166DAB5</tstamp>
    </comp>
    <comp ref="R20">
      <value>4.7</value>
      <footprint>Resistor_SMD:R_0805_2012Metric_Pad1.15x1.40mm_HandSolder</footprint>
      <datasheet>~</datasheet>
      <libsource lib="Device" part="R" description="Resistor"/>
      <sheetpath names="/" tstamps="/"/>
      <tstamp>6166D1D4</tstamp>
    </comp>
    <comp ref="C25">
      <value>100nF</value>
      <footprint>Capacitor_SMD:C_0805_2012Metric_Pad1.15x1.40mm_HandSolder</footprint>
      <datasheet>~</datasheet>
      <fields>
        <field name="Mouser Part Number">80-C0805C104J5RAUTO</field>
      </fields>
      <libsource lib="Device" part="C" description="Unpolarized capacitor"/>
      <sheetpath names="/" tstamps="/"/>
      <tstamp>6167B0C2</tstamp>
    </comp>
    <comp ref="C24">
      <value>1uF</value>
      <footprint>Capacitor_SMD:C_0805_2012Metric_Pad1.15x1.40mm_HandSolder</footprint>
      <datasheet>~</datasheet>
      <fields>
        <field name="Mouser Part Number">667-EEE-FT1V561AP</field>
      </fields>
      <libsource lib="Device" part="C" description="Unpolarized capacitor"/>
      <sheetpath names="/" tstamps="/"/>
      <tstamp>6167C0ED</tstamp>
    </comp>
    <comp ref="C29">
      <value>560uF 35V</value>
      <footprint>Capacitor_SMD:CP_Elec_10x10</footprint>
      <datasheet>~</datasheet>
      <fields>
        <field name="Mouser Part Number">661-EMZS350ARA561MJA</field>
      </fields>
      <libsource lib="Device" part="CP1_Small" description="Polarized capacitor, small US symbol"/>
      <sheetpath names="/" tstamps="/"/>
      <tstamp>616902B5</tstamp>
    </comp>
    <comp ref="C32">
      <value>1uF</value>
      <footprint>Capacitor_SMD:C_0805_2012Metric_Pad1.15x1.40mm_HandSolder</footprint>
      <datasheet>~</datasheet>
      <fields>
        <field name="Mouser Part Number">667-EEE-FT1V561AP</field>
      </fields>
      <libsource lib="Device" part="C" description="Unpolarized capacitor"/>
      <sheetpath names="/" tstamps="/"/>
      <tstamp>61696DEB</tstamp>
    </comp>
    <comp ref="C30">
      <value>100nF</value>
      <footprint>Capacitor_SMD:C_0805_2012Metric_Pad1.15x1.40mm_HandSolder</footprint>
      <datasheet>~</datasheet>
      <fields>
        <field name="Mouser Part Number">80-C0805C104J5RAUTO</field>
      </fields>
      <libsource lib="Device" part="C" description="Unpolarized capacitor"/>
      <sheetpath names="/" tstamps="/"/>
      <tstamp>616977D9</tstamp>
    </comp>
    <comp ref="C31">
      <value>100nF</value>
      <footprint>Capacitor_SMD:C_0805_2012Metric_Pad1.15x1.40mm_HandSolder</footprint>
      <datasheet>~</datasheet>
      <fields>
        <field name="Mouser Part Number">80-C0805C104J5RAUTO</field>
      </fields>
      <libsource lib="Device" part="C" description="Unpolarized capacitor"/>
      <sheetpath names="/" tstamps="/"/>
      <tstamp>616A9910</tstamp>
    </comp>
    <comp ref="R23">
      <value>0.02</value>
      <footprint>Resistor_SMD:R_2512_6332Metric_Pad1.52x3.35mm_HandSolder</footprint>
      <datasheet>~</datasheet>
      <fields>
        <field name="Mouser Part Number">652-CRA2512FZ-R20ELF</field>
      </fields>
      <libsource lib="Device" part="R" description="Resistor"/>
      <sheetpath names="/" tstamps="/"/>
      <tstamp>616C7664</tstamp>
    </comp>
    <comp ref="R24">
      <value>0.02</value>
      <footprint>Resistor_SMD:R_2512_6332Metric_Pad1.52x3.35mm_HandSolder</footprint>
      <datasheet>~</datasheet>
      <fields>
        <field name="Mouser Part Number">652-CRA2512FZ-R20ELF</field>
      </fields>
      <libsource lib="Device" part="R" description="Resistor"/>
      <sheetpath names="/" tstamps="/"/>
      <tstamp>616D76A2</tstamp>
    </comp>
    <comp ref="U1">
      <value>MC78L08_SO8</value>
      <footprint>Package_SO:SOIC-8_3.9x4.9mm_P1.27mm</footprint>
      <datasheet>http://www.fairchildsemi.com/ds/LM/LM78L05A.pdf</datasheet>
      <fields>
        <field name="Mouser Part Number">511-L78L08ACD-TR</field>
      </fields>
      <libsource lib="Regulator_Linear" part="MC78L08_SO8" description="Positive 100mA 30V Linear Regulator, Fixed Output 8V, SO-8"/>
      <sheetpath names="/" tstamps="/"/>
      <tstamp>616E5867</tstamp>
    </comp>
    <comp ref="C35">
      <value>1uF</value>
      <footprint>Capacitor_SMD:C_0805_2012Metric_Pad1.15x1.40mm_HandSolder</footprint>
      <datasheet>~</datasheet>
      <fields>
        <field name="Mouser Part Number">80-C0805C104J5RAUTO</field>
      </fields>
      <libsource lib="Device" part="C" description="Unpolarized capacitor"/>
      <sheetpath names="/" tstamps="/"/>
      <tstamp>616F322B</tstamp>
    </comp>
    <comp ref="C28">
      <value>10uF/35V</value>
      <footprint>Capacitor_SMD:C_1206_3216Metric_Pad1.42x1.75mm_HandSolder</footprint>
      <datasheet>~</datasheet>
      <fields>
        <field name="Mouser Part Number">GMK316AB7106KL-TR</field>
      </fields>
      <libsource lib="Device" part="C" description="Unpolarized capacitor"/>
      <sheetpath names="/" tstamps="/"/>
      <tstamp>616F3DA0</tstamp>
    </comp>
    <comp ref="C34">
      <value>1uF</value>
      <footprint>Capacitor_SMD:C_0805_2012Metric_Pad1.15x1.40mm_HandSolder</footprint>
      <datasheet>~</datasheet>
      <fields>
        <field name="Mouser Part Number">80-C0805C104J5RAUTO</field>
      </fields>
      <libsource lib="Device" part="C" description="Unpolarized capacitor"/>
      <sheetpath names="/" tstamps="/"/>
      <tstamp>6170A3BE</tstamp>
    </comp>
    <comp ref="D6">
      <value>MBRS2545CT RN</value>
      <footprint>Package_TO_SOT_SMD:TO-263-3_TabPin4</footprint>
      <datasheet>https://www.mouser.com/datasheet/2/395/MBRS2535CT_SERIES_M15-1918202.pdf</datasheet>
      <fields>
        <field name="Mouser Part Number">821-MBRS2545CTRN</field>
      </fields>
      <libsource lib="Device" part="D_x2_KCom_AAK" description="Dual diode, common cathode on pin 3"/>
      <sheetpath names="/" tstamps="/"/>
      <tstamp>6171C331</tstamp>
    </comp>
    <comp ref="R25">
      <value>10K</value>
      <footprint>Resistor_SMD:R_0805_2012Metric_Pad1.15x1.40mm_HandSolder</footprint>
      <datasheet>~</datasheet>
      <libsource lib="Device" part="R" description="Resistor"/>
      <sheetpath names="/" tstamps="/"/>
      <tstamp>6174A6E7</tstamp>
    </comp>
    <comp ref="T3">
      <value>BSS84</value>
      <footprint>Package_TO_SOT_SMD:SOT-23</footprint>
      <datasheet>https://www.mouser.com/datasheet/2/916/BSS84AK-1598662.pdf</datasheet>
      <fields>
        <field name="Mouser Part Number">771-BSS84AKVL</field>
      </fields>
      <libsource lib="Device" part="Q_PMOS_GSD" description="P-MOSFET transistor, gate/source/drain"/>
      <sheetpath names="/" tstamps="/"/>
      <tstamp>61758C2F</tstamp>
    </comp>
    <comp ref="J3">
      <value>Conn_01x02_Male</value>
      <footprint>Connector_PinHeader_2.54mm:PinHeader_1x02_P2.54mm_Vertical</footprint>
      <datasheet>~</datasheet>
      <libsource lib="Connector" part="Conn_01x02_Male" description="Generic connector, single row, 01x02, script generated (kicad-library-utils/schlib/autogen/connector/)"/>
      <sheetpath names="/" tstamps="/"/>
      <tstamp>6176ADB7</tstamp>
    </comp>
    <comp ref="D5">
      <value>1N4001</value>
      <footprint>Diode_SMD:D_0805_2012Metric_Pad1.15x1.40mm_HandSolder</footprint>
      <datasheet>http://www.vishay.com/docs/88503/1n4001.pdf</datasheet>
      <libsource lib="Diode" part="1N4001" description="50V 1A General Purpose Rectifier Diode, DO-41"/>
      <sheetpath names="/" tstamps="/"/>
      <tstamp>6177246C</tstamp>
    </comp>
    <comp ref="C27">
      <value>0.1uF</value>
      <footprint>Capacitor_SMD:C_0805_2012Metric_Pad1.15x1.40mm_HandSolder</footprint>
      <datasheet>~</datasheet>
      <libsource lib="Device" part="C" description="Unpolarized capacitor"/>
      <sheetpath names="/" tstamps="/"/>
      <tstamp>6178F9ED</tstamp>
    </comp>
    <comp ref="L5">
      <value>FB</value>
      <footprint>Inductor_SMD:L_MUNIN_FB</footprint>
      <datasheet>~</datasheet>
      <fields>
        <field name="Mouser Part Number">704-MFBM1V2012-101-R </field>
      </fields>
      <libsource lib="Device" part="L" description="Inductor"/>
      <sheetpath names="/" tstamps="/"/>
      <tstamp>617B1DEF</tstamp>
    </comp>
    <comp ref="R1">
      <value>2K</value>
      <footprint>Potentiometer_THT:Potentiometer_Bourns_3386P_Vertical</footprint>
      <datasheet>https://www.mouser.com/datasheet/2/54/pv12-907348.pdf</datasheet>
      <fields>
        <field name="Mouser Part Number">81-PV12P202A01B00</field>
      </fields>
      <libsource lib="Device" part="R_POT" description="Potentiometer"/>
      <sheetpath names="/" tstamps="/"/>
      <tstamp>617D7CCD</tstamp>
    </comp>
    <comp ref="R22">
      <value>2K</value>
      <footprint>Potentiometer_THT:Potentiometer_Bourns_3386P_Vertical</footprint>
      <datasheet>https://www.mouser.com/datasheet/2/54/pv12-907348.pdf</datasheet>
      <fields>
        <field name="Mouser Part Number">81-PV12P202A01B00</field>
      </fields>
      <libsource lib="Device" part="R_POT" description="Potentiometer"/>
      <sheetpath names="/" tstamps="/"/>
      <tstamp>617DA550</tstamp>
    </comp>
    <comp ref="R2">
      <value>1K</value>
      <footprint>Resistor_SMD:R_0805_2012Metric_Pad1.15x1.40mm_HandSolder</footprint>
      <datasheet>~</datasheet>
      <libsource lib="Device" part="R" description="Resistor"/>
      <sheetpath names="/" tstamps="/"/>
      <tstamp>617E9BAE</tstamp>
    </comp>
    <comp ref="R21">
      <value>1K</value>
      <footprint>Resistor_SMD:R_0805_2012Metric_Pad1.15x1.40mm_HandSolder</footprint>
      <datasheet>~</datasheet>
      <libsource lib="Device" part="R" description="Resistor"/>
      <sheetpath names="/" tstamps="/"/>
      <tstamp>617EAE8F</tstamp>
    </comp>
    <comp ref="C26">
      <value>10uF/35V</value>
      <footprint>Capacitor_SMD:C_1206_3216Metric_Pad1.42x1.75mm_HandSolder</footprint>
      <fields>
        <field name="Mouser Part Number">GMK316AB7106KL-TR</field>
      </fields>
      <libsource lib="Device" part="C" description="Unpolarized capacitor"/>
      <sheetpath names="/" tstamps="/"/>
      <tstamp>6181DCAD</tstamp>
    </comp>
    <comp ref="C1">
      <value>0.1uF</value>
      <footprint>Capacitor_SMD:C_0805_2012Metric_Pad1.15x1.40mm_HandSolder</footprint>
      <datasheet>~</datasheet>
      <fields>
        <field name="Mouser Part Number">0805DD104KAT2A</field>
      </fields>
      <libsource lib="Device" part="C" description="Unpolarized capacitor"/>
      <sheetpath names="/" tstamps="/"/>
      <tstamp>6183DFBD</tstamp>
    </comp>
    <comp ref="C2">
      <value>10uF/35V</value>
      <footprint>Capacitor_SMD:C_1206_3216Metric_Pad1.42x1.75mm_HandSolder</footprint>
      <fields>
        <field name="Mouser Part Number">GMK316AB7106KL-TR</field>
      </fields>
      <libsource lib="Device" part="C" description="Unpolarized capacitor"/>
      <sheetpath names="/" tstamps="/"/>
      <tstamp>6183DFC4</tstamp>
    </comp>
    <comp ref="C22">
      <value>0.1uF</value>
      <footprint>Capacitor_SMD:C_0805_2012Metric_Pad1.15x1.40mm_HandSolder</footprint>
      <datasheet>~</datasheet>
      <fields>
        <field name="Mouser Part Number">0805DD104KAT2A</field>
      </fields>
      <libsource lib="Device" part="C" description="Unpolarized capacitor"/>
      <sheetpath names="/" tstamps="/"/>
      <tstamp>6181D58A</tstamp>
    </comp>
    <comp ref="C5">
      <value>0.1uF</value>
      <footprint>Capacitor_SMD:C_0805_2012Metric_Pad1.15x1.40mm_HandSolder</footprint>
      <datasheet>~</datasheet>
      <fields>
        <field name="Mouser Part Number">0805DD104KAT2A</field>
      </fields>
      <libsource lib="Device" part="C" description="Unpolarized capacitor"/>
      <sheetpath names="/" tstamps="/"/>
      <tstamp>618A9559</tstamp>
    </comp>
    <comp ref="D1">
      <value>TS4148</value>
      <footprint>Diode_SMD:D_0805_2012Metric_Pad1.15x1.40mm_HandSolder</footprint>
      <datasheet>https://www.mouser.com/datasheet/2/395/TS4148_RYG_N1803-1918648.pdf</datasheet>
      <fields>
        <field name="Mouser Part Number">821-TS4148RYG </field>
      </fields>
      <libsource lib="Device" part="D_Small" description="Diode, small symbol"/>
      <sheetpath names="/" tstamps="/"/>
      <tstamp>618C2842</tstamp>
    </comp>
    <comp ref="D4">
      <value>TS4148</value>
      <footprint>Diode_SMD:D_0805_2012Metric_Pad1.15x1.40mm_HandSolder</footprint>
      <datasheet>https://www.mouser.com/datasheet/2/395/TS4148_RYG_N1803-1918648.pdf</datasheet>
      <fields>
        <field name="Mouser Part Number">821-TS4148RYG </field>
      </fields>
      <libsource lib="Device" part="D_Small" description="Diode, small symbol"/>
      <sheetpath names="/" tstamps="/"/>
      <tstamp>618C34A0</tstamp>
    </comp>
    <comp ref="R3">
      <value>22</value>
      <footprint>Resistor_SMD:R_0805_2012Metric_Pad1.15x1.40mm_HandSolder</footprint>
      <datasheet>~</datasheet>
      <libsource lib="Device" part="R" description="Resistor"/>
      <sheetpath names="/" tstamps="/"/>
      <tstamp>618ECC81</tstamp>
    </comp>
    <comp ref="D2">
      <value>TS4148</value>
      <footprint>Diode_SMD:D_0805_2012Metric_Pad1.15x1.40mm_HandSolder</footprint>
      <datasheet>https://www.mouser.com/datasheet/2/395/TS4148_RYG_N1803-1918648.pdf</datasheet>
      <fields>
        <field name="Mouser Part Number">821-TS4148RYG </field>
      </fields>
      <libsource lib="Device" part="D_Small" description="Diode, small symbol"/>
      <sheetpath names="/" tstamps="/"/>
      <tstamp>619184DE</tstamp>
    </comp>
    <comp ref="D3">
      <value>TS4148</value>
      <footprint>Diode_SMD:D_0805_2012Metric_Pad1.15x1.40mm_HandSolder</footprint>
      <datasheet>https://www.mouser.com/datasheet/2/395/TS4148_RYG_N1803-1918648.pdf</datasheet>
      <fields>
        <field name="Mouser Part Number">821-TS4148RYG </field>
      </fields>
      <libsource lib="Device" part="D_Small" description="Diode, small symbol"/>
      <sheetpath names="/" tstamps="/"/>
      <tstamp>6191A5EC</tstamp>
    </comp>
    <comp ref="R17">
      <value>22</value>
      <footprint>Resistor_SMD:R_0805_2012Metric_Pad1.15x1.40mm_HandSolder</footprint>
      <datasheet>~</datasheet>
      <libsource lib="Device" part="R" description="Resistor"/>
      <sheetpath names="/" tstamps="/"/>
      <tstamp>618CE90A</tstamp>
    </comp>
    <comp ref="R16">
      <value>3.9K</value>
      <footprint>Resistor_SMD:R_0805_2012Metric_Pad1.15x1.40mm_HandSolder</footprint>
      <datasheet>~</datasheet>
      <libsource lib="Device" part="R" description="Resistor"/>
      <sheetpath names="/" tstamps="/"/>
      <tstamp>6193DCB2</tstamp>
    </comp>
    <comp ref="R14">
      <value>NTC 10K</value>
      <footprint>Resistor_THT:R_Axial_DIN0204_L3.6mm_D1.6mm_P2.54mm_Vertical</footprint>
      <datasheet>~</datasheet>
      <libsource lib="Device" part="R" description="Resistor"/>
      <sheetpath names="/" tstamps="/"/>
      <tstamp>619563A6</tstamp>
    </comp>
    <comp ref="C37">
      <value>0.01uF</value>
      <footprint>Capacitor_SMD:C_0805_2012Metric_Pad1.15x1.40mm_HandSolder</footprint>
      <datasheet>~</datasheet>
      <fields>
        <field name="Mouser Part Number">80-C0805C103K5TAUTO</field>
      </fields>
      <libsource lib="Device" part="C" description="Unpolarized capacitor"/>
      <sheetpath names="/" tstamps="/"/>
      <tstamp>6197D5E3</tstamp>
    </comp>
    <comp ref="R27">
      <value>50</value>
      <footprint>Resistor_SMD:R_0805_2012Metric_Pad1.15x1.40mm_HandSolder</footprint>
      <datasheet>~</datasheet>
      <libsource lib="Device" part="R" description="Resistor"/>
      <sheetpath names="/" tstamps="/"/>
      <tstamp>6198D7B3</tstamp>
    </comp>
    <comp ref="U2">
      <value>LMC6482</value>
      <footprint>Package_SO:SOIC-8_3.9x4.9mm_P1.27mm</footprint>
      <datasheet>http://www.ti.com/lit/ds/symlink/lmc6482.pdf</datasheet>
      <libsource lib="Amplifier_Operational" part="LMC6482" description="Dual CMOS Rail-to-Rail Input and Output Operational Amplifier, DIP-8/SOIC-8, SSOP-8"/>
      <sheetpath names="/" tstamps="/"/>
      <tstamp>6198E941</tstamp>
    </comp>
    <comp ref="T4">
      <value>BST82</value>
      <footprint>Package_TO_SOT_SMD:SOT-23</footprint>
      <datasheet>https://www.mouser.com/datasheet/2/916/BST82-1320196.pdf</datasheet>
      <fields>
        <field name="Mouser Part Number">771-BST82235</field>
      </fields>
      <libsource lib="Device" part="Q_NMOS_DGS" description="N-MOSFET transistor, drain/gate/source"/>
      <sheetpath names="/" tstamps="/"/>
      <tstamp>619935E0</tstamp>
    </comp>
    <comp ref="R26">
      <value>1K</value>
      <footprint>Resistor_SMD:R_0805_2012Metric_Pad1.15x1.40mm_HandSolder</footprint>
      <datasheet>~</datasheet>
      <libsource lib="Device" part="R" description="Resistor"/>
      <sheetpath names="/" tstamps="/"/>
      <tstamp>619EE43A</tstamp>
    </comp>
    <comp ref="J4">
      <value>Conn_01x02_Male</value>
      <footprint>Connector_PinHeader_2.54mm:PinHeader_1x02_P2.54mm_Vertical</footprint>
      <datasheet>~</datasheet>
      <libsource lib="Connector" part="Conn_01x02_Male" description="Generic connector, single row, 01x02, script generated (kicad-library-utils/schlib/autogen/connector/)"/>
      <sheetpath names="/" tstamps="/"/>
      <tstamp>61A992DC</tstamp>
    </comp>
    <comp ref="C33">
      <value>0.01uF</value>
      <footprint>Capacitor_SMD:C_0805_2012Metric_Pad1.15x1.40mm_HandSolder</footprint>
      <datasheet>~</datasheet>
      <fields>
        <field name="Mouser Part Number">80-C0805C103K5TAUTO</field>
      </fields>
      <libsource lib="Device" part="C" description="Unpolarized capacitor"/>
      <sheetpath names="/" tstamps="/"/>
      <tstamp>61AD598F</tstamp>
    </comp>
    <comp ref="C11">
      <value>220pF/500V/NPO</value>
      <footprint>Capacitor_SMD:C_1206_3216Metric_Pad1.42x1.75mm_HandSolder</footprint>
      <datasheet>~</datasheet>
      <fields>
        <field name="Mouser Part Number">81-GRM31A5C2H221JW1D</field>
      </fields>
      <libsource lib="Device" part="C" description="Unpolarized capacitor"/>
      <sheetpath names="/" tstamps="/"/>
      <tstamp>61AEB65A</tstamp>
    </comp>
    <comp ref="C10">
      <value>220pF/500V/NPO</value>
      <footprint>Capacitor_SMD:C_1206_3216Metric_Pad1.42x1.75mm_HandSolder</footprint>
      <datasheet>~</datasheet>
      <fields>
        <field name="Mouser Part Number">81-GRM31A5C2H221JW1D</field>
      </fields>
      <libsource lib="Device" part="C" description="Unpolarized capacitor"/>
      <sheetpath names="/" tstamps="/"/>
      <tstamp>61AEC64C</tstamp>
    </comp>
    <comp ref="J2">
      <value>Conn_Coaxial</value>
      <footprint>Connector_Coaxial:SMA_Amphenol_132291_Vertical</footprint>
      <datasheet> ~</datasheet>
      <libsource lib="Connector" part="Conn_Coaxial" description="coaxial connector (BNC, SMA, SMB, SMC, Cinch/RCA, ...)"/>
      <sheetpath names="/" tstamps="/"/>
      <tstamp>61C770C1</tstamp>
    </comp>
    <comp ref="J1">
      <value>Conn_Coaxial</value>
      <footprint>Connector_Coaxial:SMA_Amphenol_132291_Vertical</footprint>
      <datasheet> ~</datasheet>
      <libsource lib="Connector" part="Conn_Coaxial" description="coaxial connector (BNC, SMA, SMB, SMC, Cinch/RCA, ...)"/>
      <sheetpath names="/" tstamps="/"/>
      <tstamp>61C8887F</tstamp>
    </comp>
    <comp ref="T2">
      <value>Q_NMOS_DSG</value>
      <footprint>RF_Module:RD100HHF1</footprint>
      <datasheet>~</datasheet>
      <libsource lib="Device" part="Q_NMOS_DSG" description="N-MOSFET transistor, drain/source/gate"/>
      <sheetpath names="/" tstamps="/"/>
      <tstamp>61CBAA0A</tstamp>
    </comp>
    <comp ref="T1">
      <value>Q_NMOS_DSG</value>
      <footprint>RF_Module:RD100HHF1</footprint>
      <datasheet>~</datasheet>
      <libsource lib="Device" part="Q_NMOS_DSG" description="N-MOSFET transistor, drain/source/gate"/>
      <sheetpath names="/" tstamps="/"/>
      <tstamp>61CBC00C</tstamp>
    </comp>
    <comp ref="H1">
      <value>+24V</value>
      <footprint>MountingHole:MountingHole_11mm_M4_square_Via</footprint>
      <datasheet>~</datasheet>
      <libsource lib="Mechanical" part="MountingHole_Pad" description="Mounting Hole with connection"/>
      <sheetpath names="/" tstamps="/"/>
      <tstamp>61D1C8BC</tstamp>
    </comp>
    <comp ref="H2">
      <value>GND</value>
      <footprint>MountingHole:MountingHole_11mm_M4_square_Via</footprint>
      <datasheet>~</datasheet>
      <libsource lib="Mechanical" part="MountingHole_Pad" description="Mounting Hole with connection"/>
      <sheetpath names="/" tstamps="/"/>
      <tstamp>61D4D401</tstamp>
    </comp>
    <comp ref="C23">
      <value>560uF 35V</value>
      <footprint>Capacitor_SMD:CP_Elec_10x10</footprint>
      <datasheet>~</datasheet>
      <fields>
        <field name="Mouser Part Number">661-EMZS350ARA561MJA</field>
      </fields>
      <libsource lib="Device" part="CP1_Small" description="Polarized capacitor, small US symbol"/>
      <sheetpath names="/" tstamps="/"/>
      <tstamp>61D63D48</tstamp>
    </comp>
  </components>
  <libparts>
    <libpart lib="Amplifier_Operational" part="LM2904">
      <aliases>
        <alias>LM358</alias>
        <alias>AD8620</alias>
        <alias>LMC6062</alias>
        <alias>LMC6082</alias>
        <alias>TL062</alias>
        <alias>TL072</alias>
        <alias>TL082</alias>
        <alias>NE5532</alias>
        <alias>SA5532</alias>
        <alias>RC4558</alias>
        <alias>RC4560</alias>
        <alias>RC4580</alias>
        <alias>LMV358</alias>
        <alias>TS912</alias>
        <alias>TSV912IDT</alias>
        <alias>TSV912IST</alias>
        <alias>TLC272</alias>
        <alias>TLC277</alias>
        <alias>MCP602</alias>
        <alias>OPA2134</alias>
        <alias>OPA2340</alias>
        <alias>OPA2376xxD</alias>
        <alias>OPA2376xxDGK</alias>
        <alias>MC33078</alias>
        <alias>MC33178</alias>
        <alias>LM4562</alias>
        <alias>OP249</alias>
        <alias>OP275</alias>
        <alias>ADA4075-2</alias>
        <alias>MCP6002-xP</alias>
        <alias>MCP6002-xSN</alias>
        <alias>MCP6002-xMS</alias>
        <alias>LM7332</alias>
        <alias>OPA2333xxD</alias>
        <alias>OPA2333xxDGK</alias>
        <alias>LMC6482</alias>
        <alias>LT1492</alias>
        <alias>LTC6081xMS8</alias>
        <alias>LM6172</alias>
        <alias>MCP6L92</alias>
        <alias>NJM2043</alias>
        <alias>NJM2114</alias>
        <alias>NJM4556A</alias>
        <alias>NJM4558</alias>
        <alias>NJM4559</alias>
        <alias>NJM4560</alias>
        <alias>NJM4580</alias>
        <alias>NJM5532</alias>
        <alias>ADA4807-2ARM</alias>
        <alias>OPA2691</alias>
        <alias>LT6233</alias>
        <alias>OPA2356xxD</alias>
        <alias>OPA2356xxDGK</alias>
        <alias>OPA1612AxD</alias>
        <alias>MC33172</alias>
        <alias>OPA1602</alias>
        <alias>TLV2372</alias>
      </aliases>
      <description>Dual Operational Amplifiers, DIP-8/SOIC-8/TSSOP-8/VSSOP-8</description>
      <docs>http://www.ti.com/lit/ds/symlink/lm358.pdf</docs>
      <footprints>
        <fp>SOIC*3.9x4.9mm*P1.27mm*</fp>
        <fp>DIP*W7.62mm*</fp>
        <fp>TO*99*</fp>
        <fp>OnSemi*Micro8*</fp>
        <fp>TSSOP*3x3mm*P0.65mm*</fp>
        <fp>TSSOP*4.4x3mm*P0.65mm*</fp>
        <fp>MSOP*3x3mm*P0.65mm*</fp>
        <fp>SSOP*3.9x4.9mm*P0.635mm*</fp>
        <fp>LFCSP*2x2mm*P0.5mm*</fp>
        <fp>*SIP*</fp>
        <fp>SOIC*5.3x6.2mm*P1.27mm*</fp>
      </footprints>
      <fields>
        <field name="Reference">U</field>
        <field name="Value">LM2904</field>
      </fields>
      <pins>
        <pin num="1" name="~" type="output"/>
        <pin num="2" name="-" type="input"/>
        <pin num="3" name="+" type="input"/>
        <pin num="4" name="V-" type="power_in"/>
        <pin num="5" name="+" type="input"/>
        <pin num="6" name="-" type="input"/>
        <pin num="7" name="~" type="output"/>
        <pin num="8" name="V+" type="power_in"/>
      </pins>
    </libpart>
    <libpart lib="Connector" part="Conn_01x02_Male">
      <description>Generic connector, single row, 01x02, script generated (kicad-library-utils/schlib/autogen/connector/)</description>
      <docs>~</docs>
      <footprints>
        <fp>Connector*:*_1x??_*</fp>
      </footprints>
      <fields>
        <field name="Reference">J</field>
        <field name="Value">Conn_01x02_Male</field>
      </fields>
      <pins>
        <pin num="1" name="Pin_1" type="passive"/>
        <pin num="2" name="Pin_2" type="passive"/>
      </pins>
    </libpart>
    <libpart lib="Connector" part="Conn_Coaxial">
      <description>coaxial connector (BNC, SMA, SMB, SMC, Cinch/RCA, ...)</description>
      <docs> ~</docs>
      <footprints>
        <fp>*BNC*</fp>
        <fp>*SMA*</fp>
        <fp>*SMB*</fp>
        <fp>*SMC*</fp>
        <fp>*Cinch*</fp>
      </footprints>
      <fields>
        <field name="Reference">J</field>
        <field name="Value">Conn_Coaxial</field>
      </fields>
      <pins>
        <pin num="1" name="In" type="passive"/>
        <pin num="2" name="Ext" type="passive"/>
      </pins>
    </libpart>
    <libpart lib="Device" part="C">
      <description>Unpolarized capacitor</description>
      <docs>~</docs>
      <footprints>
        <fp>C_*</fp>
      </footprints>
      <fields>
        <field name="Reference">C</field>
        <field name="Value">C</field>
      </fields>
      <pins>
        <pin num="1" name="~" type="passive"/>
        <pin num="2" name="~" type="passive"/>
      </pins>
    </libpart>
    <libpart lib="Device" part="CP1_Small">
      <description>Polarized capacitor, small US symbol</description>
      <docs>~</docs>
      <footprints>
        <fp>CP_*</fp>
      </footprints>
      <fields>
        <field name="Reference">C</field>
        <field name="Value">CP1_Small</field>
      </fields>
      <pins>
        <pin num="1" name="~" type="passive"/>
        <pin num="2" name="~" type="passive"/>
      </pins>
    </libpart>
    <libpart lib="Device" part="D_Small">
      <description>Diode, small symbol</description>
      <docs>~</docs>
      <footprints>
        <fp>TO-???*</fp>
        <fp>*_Diode_*</fp>
        <fp>*SingleDiode*</fp>
        <fp>D_*</fp>
      </footprints>
      <fields>
        <field name="Reference">D</field>
        <field name="Value">D_Small</field>
      </fields>
      <pins>
        <pin num="1" name="K" type="passive"/>
        <pin num="2" name="A" type="passive"/>
      </pins>
    </libpart>
    <libpart lib="Device" part="D_x2_KCom_AAK">
      <description>Dual diode, common cathode on pin 3</description>
      <docs>~</docs>
      <fields>
        <field name="Reference">D</field>
        <field name="Value">D_x2_KCom_AAK</field>
      </fields>
      <pins>
        <pin num="1" name="A" type="passive"/>
        <pin num="2" name="A" type="passive"/>
        <pin num="3" name="K" type="passive"/>
      </pins>
    </libpart>
    <libpart lib="Device" part="L">
      <description>Inductor</description>
      <docs>~</docs>
      <footprints>
        <fp>Choke_*</fp>
        <fp>*Coil*</fp>
        <fp>Inductor_*</fp>
        <fp>L_*</fp>
      </footprints>
      <fields>
        <field name="Reference">L</field>
        <field name="Value">L</field>
      </fields>
      <pins>
        <pin num="1" name="1" type="passive"/>
        <pin num="2" name="2" type="passive"/>
      </pins>
    </libpart>
    <libpart lib="Device" part="L_Core_Iron_Small">
      <description>Inductor with iron core, small symbol</description>
      <docs>~</docs>
      <footprints>
        <fp>Choke_*</fp>
        <fp>*Coil*</fp>
        <fp>Inductor_*</fp>
        <fp>L_*</fp>
      </footprints>
      <fields>
        <field name="Reference">L</field>
        <field name="Value">L_Core_Iron_Small</field>
      </fields>
      <pins>
        <pin num="1" name="~" type="passive"/>
        <pin num="2" name="~" type="passive"/>
      </pins>
    </libpart>
    <libpart lib="Device" part="Q_NMOS_DGS">
      <description>N-MOSFET transistor, drain/gate/source</description>
      <docs>~</docs>
      <fields>
        <field name="Reference">Q</field>
        <field name="Value">Q_NMOS_DGS</field>
      </fields>
      <pins>
        <pin num="1" name="D" type="passive"/>
        <pin num="2" name="G" type="input"/>
        <pin num="3" name="S" type="passive"/>
      </pins>
    </libpart>
    <libpart lib="Device" part="Q_NMOS_DSG">
      <description>N-MOSFET transistor, drain/source/gate</description>
      <docs>~</docs>
      <fields>
        <field name="Reference">Q</field>
        <field name="Value">Q_NMOS_DSG</field>
      </fields>
      <pins>
        <pin num="1" name="D" type="passive"/>
        <pin num="2" name="S" type="passive"/>
        <pin num="3" name="G" type="input"/>
      </pins>
    </libpart>
    <libpart lib="Device" part="Q_PMOS_GSD">
      <description>P-MOSFET transistor, gate/source/drain</description>
      <docs>~</docs>
      <fields>
        <field name="Reference">Q</field>
        <field name="Value">Q_PMOS_GSD</field>
      </fields>
      <pins>
        <pin num="1" name="G" type="input"/>
        <pin num="2" name="S" type="passive"/>
        <pin num="3" name="D" type="passive"/>
      </pins>
    </libpart>
    <libpart lib="Device" part="R">
      <description>Resistor</description>
      <docs>~</docs>
      <footprints>
        <fp>R_*</fp>
      </footprints>
      <fields>
        <field name="Reference">R</field>
        <field name="Value">R</field>
      </fields>
      <pins>
        <pin num="1" name="~" type="passive"/>
        <pin num="2" name="~" type="passive"/>
      </pins>
    </libpart>
    <libpart lib="Device" part="R_POT">
      <description>Potentiometer</description>
      <docs>~</docs>
      <footprints>
        <fp>Potentiometer*</fp>
      </footprints>
      <fields>
        <field name="Reference">RV</field>
        <field name="Value">R_POT</field>
      </fields>
      <pins>
        <pin num="1" name="1" type="passive"/>
        <pin num="2" name="2" type="passive"/>
        <pin num="3" name="3" type="passive"/>
      </pins>
    </libpart>
    <libpart lib="Device" part="Transformer_1P_1S">
      <description>Transformer, single primary, single secondary</description>
      <docs>~</docs>
      <fields>
        <field name="Reference">T</field>
        <field name="Value">Transformer_1P_1S</field>
      </fields>
      <pins>
        <pin num="1" name="AA" type="passive"/>
        <pin num="2" name="AB" type="passive"/>
        <pin num="3" name="SB" type="passive"/>
        <pin num="4" name="SA" type="passive"/>
      </pins>
    </libpart>
    <libpart lib="Device" part="Transformer_1P_SS">
      <description>Transformer, single primary, split secondary</description>
      <docs>~</docs>
      <fields>
        <field name="Reference">T</field>
        <field name="Value">Transformer_1P_SS</field>
      </fields>
      <pins>
        <pin num="1" name="AA" type="passive"/>
        <pin num="2" name="AB" type="passive"/>
        <pin num="3" name="SA" type="passive"/>
        <pin num="4" name="SC" type="passive"/>
        <pin num="5" name="SB" type="passive"/>
      </pins>
    </libpart>
    <libpart lib="Diode" part="1N4001">
      <aliases>
        <alias>1N4002</alias>
        <alias>1N4003</alias>
        <alias>1N4004</alias>
        <alias>1N4005</alias>
        <alias>1N4006</alias>
        <alias>1N4007</alias>
        <alias>BA157</alias>
        <alias>BA158</alias>
        <alias>BA159</alias>
      </aliases>
      <description>50V 1A General Purpose Rectifier Diode, DO-41</description>
      <docs>http://www.vishay.com/docs/88503/1n4001.pdf</docs>
      <footprints>
        <fp>D*DO?41*</fp>
      </footprints>
      <fields>
        <field name="Reference">D</field>
        <field name="Value">1N4001</field>
        <field name="Footprint">Diode_THT:D_DO-41_SOD81_P10.16mm_Horizontal</field>
      </fields>
      <pins>
        <pin num="1" name="K" type="passive"/>
        <pin num="2" name="A" type="passive"/>
      </pins>
    </libpart>
    <libpart lib="Mechanical" part="MountingHole_Pad">
      <description>Mounting Hole with connection</description>
      <docs>~</docs>
      <footprints>
        <fp>MountingHole*Pad*</fp>
      </footprints>
      <fields>
        <field name="Reference">H</field>
        <field name="Value">MountingHole_Pad</field>
      </fields>
      <pins>
        <pin num="1" name="1" type="input"/>
      </pins>
    </libpart>
    <libpart lib="Regulator_Linear" part="MC78L05_SO8">
      <aliases>
        <alias>MC78L08_SO8</alias>
        <alias>MC78L06_SO8</alias>
        <alias>MC78L12_SO8</alias>
        <alias>MC78L15_SO8</alias>
        <alias>MC78L18_SO8</alias>
        <alias>MC78L24_SO8</alias>
        <alias>LM78L05_SO8</alias>
        <alias>LM78L12_SO8</alias>
        <alias>LM2931-5.0_SO8</alias>
        <alias>L78L33_SO8</alias>
        <alias>L78L05_SO8</alias>
        <alias>L78L06_SO8</alias>
        <alias>L78L08_SO8</alias>
        <alias>L78L09_SO8</alias>
        <alias>L78L10_SO8</alias>
        <alias>L78L12_SO8</alias>
        <alias>L78L15_SO8</alias>
        <alias>L78L18_SO8</alias>
        <alias>L78L24_SO8</alias>
      </aliases>
      <description>Positive 100mA 30V Linear Regulator, Fixed Output 5V, SO-8</description>
      <docs>http://www.fairchildsemi.com/ds/LM/LM78L05A.pdf</docs>
      <footprints>
        <fp>SOIC*3.9x4.9mm*P1.27mm*</fp>
      </footprints>
      <fields>
        <field name="Reference">U</field>
        <field name="Value">MC78L05_SO8</field>
        <field name="Footprint">Package_SO:SOIC-8_3.9x4.9mm_P1.27mm</field>
      </fields>
      <pins>
        <pin num="1" name="OUT" type="power_out"/>
        <pin num="2" name="GND" type="passive"/>
        <pin num="3" name="GND" type="passive"/>
        <pin num="4" name="NC" type="NotConnected"/>
        <pin num="5" name="NC" type="NotConnected"/>
        <pin num="6" name="GND" type="passive"/>
        <pin num="7" name="GND" type="power_in"/>
        <pin num="8" name="IN" type="power_in"/>
      </pins>
    </libpart>
  </libparts>
  <libraries>
    <library logical="Amplifier_Operational">
      <uri>/usr/share/kicad/library//Amplifier_Operational.lib</uri>
    </library>
    <library logical="Connector">
      <uri>/usr/share/kicad/library//Connector.lib</uri>
    </library>
    <library logical="Device">
      <uri>/usr/share/kicad/library//Device.lib</uri>
    </library>
    <library logical="Diode">
      <uri>/usr/share/kicad/library//Diode.lib</uri>
    </library>
    <library logical="Mechanical">
      <uri>/usr/share/kicad/library//Mechanical.lib</uri>
    </library>
    <library logical="Regulator_Linear">
      <uri>/usr/share/kicad/library//Regulator_Linear.lib</uri>
    </library>
  </libraries>
  <nets>
    <net code="1" name="GND">
      <node ref="C34" pin="2"/>
      <node ref="T1" pin="2"/>
      <node ref="H2" pin="1"/>
      <node ref="C27" pin="2"/>
      <node ref="R9" pin="2"/>
      <node ref="C23" pin="2"/>
      <node ref="R10" pin="1"/>
      <node ref="C35" pin="2"/>
      <node ref="U2" pin="4"/>
      <node ref="U1" pin="6"/>
      <node ref="C29" pin="2"/>
      <node ref="C33" pin="2"/>
      <node ref="U1" pin="7"/>
      <node ref="C32" pin="2"/>
      <node ref="C30" pin="2"/>
      <node ref="J4" pin="1"/>
      <node ref="C31" pin="2"/>
      <node ref="U1" pin="3"/>
      <node ref="J3" pin="2"/>
      <node ref="U1" pin="2"/>
      <node ref="C37" pin="2"/>
      <node ref="R14" pin="1"/>
      <node ref="C28" pin="2"/>
      <node ref="C1" pin="2"/>
      <node ref="C4" pin="2"/>
      <node ref="C26" pin="2"/>
      <node ref="L1" pin="1"/>
      <node ref="C2" pin="2"/>
      <node ref="R26" pin="2"/>
      <node ref="J1" pin="2"/>
      <node ref="C22" pin="2"/>
      <node ref="C16" pin="2"/>
      <node ref="J2" pin="2"/>
      <node ref="D6" pin="1"/>
      <node ref="D6" pin="2"/>
      <node ref="C5" pin="2"/>
      <node ref="C24" pin="2"/>
      <node ref="C25" pin="2"/>
      <node ref="L3" pin="3"/>
      <node ref="T2" pin="2"/>
    </net>
    <net code="2" name="Net-(C22-Pad1)">
      <node ref="D3" pin="2"/>
      <node ref="C26" pin="1"/>
      <node ref="R21" pin="1"/>
      <node ref="C22" pin="1"/>
      <node ref="D4" pin="2"/>
    </net>
    <net code="3" name="Net-(R1-Pad1)">
      <node ref="R1" pin="1"/>
      <node ref="R2" pin="2"/>
    </net>
    <net code="4" name="Net-(R21-Pad2)">
      <node ref="R22" pin="1"/>
      <node ref="R21" pin="2"/>
    </net>
    <net code="5" name="/8VBIAS">
      <node ref="C5" pin="1"/>
      <node ref="R22" pin="3"/>
      <node ref="R22" pin="2"/>
      <node ref="T3" pin="3"/>
      <node ref="R1" pin="3"/>
      <node ref="R1" pin="2"/>
      <node ref="C27" pin="1"/>
    </net>
    <net code="6" name="Net-(D4-Pad1)">
      <node ref="R17" pin="2"/>
      <node ref="D4" pin="1"/>
    </net>
    <net code="7" name="Net-(D5-Pad2)">
      <node ref="D5" pin="2"/>
      <node ref="R25" pin="1"/>
      <node ref="T3" pin="1"/>
    </net>
    <net code="8" name="Net-(C28-Pad1)">
      <node ref="U1" pin="8"/>
      <node ref="C28" pin="1"/>
      <node ref="L5" pin="2"/>
      <node ref="C35" pin="1"/>
    </net>
    <net code="9" name="/+8V">
      <node ref="U1" pin="1"/>
      <node ref="R25" pin="2"/>
      <node ref="T3" pin="2"/>
      <node ref="C34" pin="1"/>
    </net>
    <net code="10" name="Net-(R27-Pad2)">
      <node ref="R27" pin="2"/>
      <node ref="T4" pin="1"/>
      <node ref="U2" pin="3"/>
    </net>
    <net code="11" name="Net-(C33-Pad1)">
      <node ref="C33" pin="1"/>
      <node ref="R26" pin="1"/>
      <node ref="T4" pin="3"/>
      <node ref="J4" pin="2"/>
    </net>
    <net code="12" name="Net-(C1-Pad1)">
      <node ref="D2" pin="2"/>
      <node ref="C1" pin="1"/>
      <node ref="C2" pin="1"/>
      <node ref="D1" pin="2"/>
      <node ref="R2" pin="1"/>
    </net>
    <net code="13" name="Net-(R14-Pad2)">
      <node ref="R14" pin="2"/>
      <node ref="R16" pin="1"/>
    </net>
    <net code="14" name="Net-(D2-Pad1)">
      <node ref="R16" pin="2"/>
      <node ref="D3" pin="1"/>
      <node ref="D2" pin="1"/>
    </net>
    <net code="15" name="Net-(D1-Pad1)">
      <node ref="R3" pin="2"/>
      <node ref="D1" pin="1"/>
    </net>
    <net code="16" name="Net-(T4-Pad2)">
      <node ref="T4" pin="2"/>
      <node ref="U2" pin="1"/>
    </net>
    <net code="17" name="Net-(C37-Pad1)">
      <node ref="C37" pin="1"/>
      <node ref="J3" pin="1"/>
      <node ref="D5" pin="1"/>
    </net>
    <net code="18" name="Net-(C7-Pad1)">
      <node ref="C7" pin="1"/>
      <node ref="R7" pin="1"/>
      <node ref="R6" pin="1"/>
    </net>
    <net code="19" name="Net-(C10-Pad1)">
      <node ref="L2" pin="1"/>
      <node ref="C12" pin="1"/>
      <node ref="C10" pin="1"/>
      <node ref="C11" pin="1"/>
      <node ref="L3" pin="1"/>
      <node ref="T2" pin="1"/>
      <node ref="C4" pin="1"/>
    </net>
    <net code="20" name="Net-(L2-Pad3)">
      <node ref="R6" pin="2"/>
      <node ref="L2" pin="3"/>
      <node ref="R7" pin="2"/>
    </net>
    <net code="21" name="Net-(L2-Pad4)">
      <node ref="R12" pin="2"/>
      <node ref="R11" pin="2"/>
      <node ref="L2" pin="4"/>
    </net>
    <net code="22" name="Net-(C14-Pad1)">
      <node ref="R12" pin="1"/>
      <node ref="C14" pin="1"/>
      <node ref="R11" pin="1"/>
    </net>
    <net code="23" name="Net-(C6-Pad2)">
      <node ref="C8" pin="2"/>
      <node ref="R8" pin="1"/>
      <node ref="L1" pin="3"/>
      <node ref="C6" pin="2"/>
    </net>
    <net code="24" name="Net-(C13-Pad2)">
      <node ref="L1" pin="4"/>
      <node ref="R8" pin="2"/>
      <node ref="C15" pin="2"/>
      <node ref="C13" pin="2"/>
    </net>
    <net code="25" name="Net-(J2-Pad1)">
      <node ref="J2" pin="1"/>
      <node ref="L1" pin="2"/>
    </net>
    <net code="26" name="Net-(C13-Pad1)">
      <node ref="R4" pin="1"/>
      <node ref="R15" pin="1"/>
      <node ref="R9" pin="1"/>
      <node ref="R10" pin="2"/>
      <node ref="R5" pin="1"/>
      <node ref="R13" pin="1"/>
      <node ref="C6" pin="1"/>
      <node ref="C8" pin="1"/>
      <node ref="C13" pin="1"/>
      <node ref="C15" pin="1"/>
    </net>
    <net code="27" name="Net-(C7-Pad2)">
      <node ref="R3" pin="1"/>
      <node ref="C7" pin="2"/>
      <node ref="R4" pin="2"/>
      <node ref="R5" pin="2"/>
      <node ref="T2" pin="3"/>
    </net>
    <net code="28" name="Net-(C14-Pad2)">
      <node ref="T1" pin="3"/>
      <node ref="R17" pin="1"/>
      <node ref="C14" pin="2"/>
      <node ref="R15" pin="2"/>
      <node ref="R13" pin="2"/>
    </net>
    <net code="29" name="+24V">
      <node ref="C30" pin="1"/>
      <node ref="L5" pin="1"/>
      <node ref="D6" pin="3"/>
      <node ref="C32" pin="1"/>
      <node ref="C31" pin="1"/>
      <node ref="R27" pin="1"/>
      <node ref="H1" pin="1"/>
      <node ref="U2" pin="8"/>
      <node ref="C29" pin="1"/>
      <node ref="R24" pin="2"/>
      <node ref="R23" pin="2"/>
    </net>
    <net code="30" name="Net-(U1-Pad4)">
      <node ref="U1" pin="4"/>
    </net>
    <net code="31" name="Net-(U1-Pad5)">
      <node ref="U1" pin="5"/>
    </net>
    <net code="32" name="Net-(C23-Pad1)">
      <node ref="R19" pin="2"/>
      <node ref="L4" pin="2"/>
      <node ref="R18" pin="2"/>
      <node ref="R20" pin="2"/>
      <node ref="C24" pin="1"/>
      <node ref="U2" pin="2"/>
      <node ref="C25" pin="1"/>
      <node ref="R23" pin="1"/>
      <node ref="R24" pin="1"/>
      <node ref="C23" pin="1"/>
    </net>
    <net code="33" name="Net-(L3-Pad4)">
      <node ref="L4" pin="1"/>
      <node ref="R19" pin="1"/>
      <node ref="R18" pin="1"/>
      <node ref="R20" pin="1"/>
      <node ref="L3" pin="4"/>
    </net>
    <net code="34" name="Net-(J1-Pad1)">
      <node ref="L3" pin="5"/>
      <node ref="J1" pin="1"/>
    </net>
    <net code="35" name="Net-(C10-Pad2)">
      <node ref="L2" pin="2"/>
      <node ref="T1" pin="1"/>
      <node ref="C12" pin="2"/>
      <node ref="L3" pin="2"/>
      <node ref="C10" pin="2"/>
      <node ref="C11" pin="2"/>
      <node ref="C16" pin="1"/>
    </net>
  </nets>
</export>
